LICENSE
MANIFEST.in
README.md
setup.cfg
setup.py
docassemble/__init__.py
docassemble.blosign.egg-info/PKG-INFO
docassemble.blosign.egg-info/SOURCES.txt
docassemble.blosign.egg-info/dependency_links.txt
docassemble.blosign.egg-info/namespace_packages.txt
docassemble.blosign.egg-info/not-zip-safe
docassemble.blosign.egg-info/requires.txt
docassemble.blosign.egg-info/top_level.txt
docassemble/blosign/__init__.py
docassemble/blosign/blosign.py
docassemble/blosign/data/questions/blosign_test.yml
docassemble/blosign/data/sources/README.md
docassemble/blosign/data/static/README.md
docassemble/blosign/data/templates/README.md